<kategorie>
  <id>1307</id>
  <taetigkeit>Führungsaufgaben  mit Personalverantwortung in einem Museum</taetigkeit>
  <taetigkeitsbeschreibung>z.B. Ausstellungen planen, leiten und koordinieren; Ausstellungskonzepte evaluieren; sachgemäße Lagerung und Pflege von Kunstgegenständen veranlassen; Bestand pflegen und erweitern; Budget verwalten; Standards für das Personal entwickeln; Auswahl professioneller Mitarbeiter überwachen; Museum nach außen hin vertreten; Entwicklung des Museums unterstützen</taetigkeitsbeschreibung>
  <bezeichnung>Museumsleiter/in / Museumsdirektor/in</bezeichnung>
  <untergliederung>
    <default>
      <kldb schluessel="94794">Führungskräfte - Museum</kldb>
      <isco schluessel="1349">Professional services managers not elsewhere classified</isco>
      <dkz codenr="94794-100" refid="27400">Leiter/in - Museum</dkz>
    </default>
  </untergliederung>
  <abgrenzung typ="hoch" refid="1300">Kurator/in / Museologe/in</abgrenzung>
  <abgrenzung typ="mittel" refid="1303">Konservator/in</abgrenzung>
  <notes>
    <note date="1970-01-01">empty</note>
    <note date="1970-01-01">empty</note>
  </notes>
</kategorie>