<kategorie>
  <id>5167</id>
  <taetigkeit>Fertigung und Reparatur von Akkordeons, Harmonikas oder Schlaginstrumenten und Überprüfung der Klangqualität</taetigkeit>
  <taetigkeitsbeschreibung>z.B. Werkstoffe nach klang- und instrumentenspezifischen Gesichtspunkten auswählen; für den Bau von Trommeln, Congas, Bongos, Pauken, Leder und Felle nähen oder kleben sowie Trommelfelle aufziehen; Knöpfe, Tasten und Stimmstöcke montieren; Gehäuseeinzelteile zusammenfügen; Instrumente stimmen und reparieren</taetigkeitsbeschreibung>
  <bezeichnung>Handzuginstrumentenmacher/in, Harmonikamacher/in oder Schlagzeugbauer/in</bezeichnung>
  <untergliederung>
    <default>
      <kldb schluessel="93682">Musikinstrumentenbau (s.s.T.)-Fachkraft</kldb>
      <isco schluessel="7312">Musical instrument makers and tuners</isco>
      <dkz codenr="93682-100" refid="2692">Handzuginstrumentenmacher/in</dkz>
    </default>
  </untergliederung>
  <abgrenzung typ="hoch" refid="5154">Musikinstrumentenbauer/in</abgrenzung>
  <abgrenzung typ="hoch" refid="5168">Restaurator/in – Handzuginstrumente, Harmonika oder Schlaginstrumente</abgrenzung>
</kategorie>