<kategorie>
  <id>3211</id>
  <taetigkeit>Führungsaufgaben mit Personalverantwortung bei der betrieblichen Organisation und Steuerung im Unternehmen</taetigkeit>
  <taetigkeitsbeschreibung>z.B. betriebliche Prozesse und Projekte planen, organisieren und steuern; Richtlinien und Verfahren zur Unternehmensorganisation entwickeln und überwachen; auf Basis der Marktsituation unternehmerische Strategien planen; Business- und Finanzpläne erstellen und bewerten; Mitarbeiter motivieren und anleiten</taetigkeitsbeschreibung>
  <bezeichnung>Kaufmännische/r Betriebsleiter/in</bezeichnung>
  <untergliederung>
    <default>
      <kldb schluessel="71394">Führungskräfte - Unternehmensorganisation und -strategie</kldb>
      <isco schluessel="1213">Policy and planning managers</isco>
      <dkz codenr="71394-100" refid="6866">Innendienstleiter/in</dkz>
      <dkz codenr="71394-101" refid="7466">Betriebsleiter/in - kaufmännisch</dkz>
      <dkz codenr="71394-104" refid="27386">Bereichsleiter/in</dkz>
      <dkz codenr="71393-102" refid="27393">Projektleiter/in</dkz>
      <dkz codenr="71393-109" refid="29355">Gruppen-, Teamleiter/in</dkz>
    </default>
    <fragetext typ="aufsicht">
      <folgefrageAktuellerBeruf>Sind Sie befugt strategische Entscheidungen zu treffen, z.B. zur Einführung neuer Verfahren, zu finanziellen Investitionen oder zur Einstellung und Entlassung von Personal?</folgefrageAktuellerBeruf>
      <folgefrageVergangenerBeruf>Waren Sie befugt strategische Entscheidungen zu treffen, z.B. zur Einführung neuer Verfahren, zu finanziellen Investitionen oder zur Einstellung und Entlassung von Personal?</folgefrageVergangenerBeruf>
    </fragetext>
    <antwort position="1" aufsicht="Führungskraft">
      <text>Ja</text>
      <kldb schluessel="71394">Führungskräfte - Unternehmensorganisation und -strategie</kldb>
      <isco schluessel="1213">Policy and planning managers</isco>
    </antwort>
    <antwort position="2" aufsicht="Aufsichtskraft">
      <text>Nein</text>
      <kldb schluessel="71393">Aufsichtskräfte - Unternehmensorganisation und -strategie</kldb>
      <isco schluessel="3341">Office supervisors</isco>
    </antwort>
  </untergliederung>
  <abgrenzung typ="mittel" refid="3205">Technisch-kaufmännische/r Betriebassistent/in</abgrenzung>
  <abgrenzung typ="mittel" refid="3206">Betriebswirtschaftliche/r Assistent/in</abgrenzung>
  <abgrenzung typ="hoch" refid="3208">Betriebsplaner/in</abgrenzung>
  <abgrenzung typ="hoch" refid="3223">Büroleiter/in </abgrenzung>
  <abgrenzung typ="mittel" refid="2155">Leiter/in - Technische Produktionssteuerung und Qualitätssicherung</abgrenzung>
  <abgrenzung typ="hoch" refid="3201">Top-Manager/in</abgrenzung>
  <abgrenzung typ="mittel" refid="3599">Personalleiter/in</abgrenzung>
  <abgrenzung typ="mittel" refid="3570">Leiter/in Rechnungswesen/Revision/Controlling</abgrenzung>
</kategorie>